odoo9_addon_account_invoice_tax_required-9.0.1.0.0-py2.7-nspkg.pth
odoo9_addon_account_invoice_tax_required-9.0.1.0.0.dist-info/top_level.txt
odoo9_addon_account_invoice_tax_required-9.0.1.0.0.dist-info/WHEEL
odoo9_addon_account_invoice_tax_required-9.0.1.0.0.dist-info/RECORD
odoo9_addon_account_invoice_tax_required-9.0.1.0.0.dist-info/metadata.json
odoo9_addon_account_invoice_tax_required-9.0.1.0.0.dist-info/DESCRIPTION.rst
odoo9_addon_account_invoice_tax_required-9.0.1.0.0.dist-info/METADATA
odoo9_addon_account_invoice_tax_required-9.0.1.0.0.dist-info/namespace_packages.txt
odoo_addons/account_invoice_tax_required/__openerp__.py
odoo_addons/account_invoice_tax_required/__init__.py
odoo_addons/account_invoice_tax_required/README.rst
odoo_addons/account_invoice_tax_required/models/account_invoice.py
odoo_addons/account_invoice_tax_required/models/__init__.py
odoo_addons/account_invoice_tax_required/i18n/lt.po
odoo_addons/account_invoice_tax_required/i18n/zh_TW.po
odoo_addons/account_invoice_tax_required/i18n/sl.po
odoo_addons/account_invoice_tax_required/i18n/account_invoice_tax_require.pot
odoo_addons/account_invoice_tax_required/i18n/fr.po
odoo_addons/account_invoice_tax_required/i18n/pt_BR.po
odoo_addons/account_invoice_tax_required/tests/__init__.py
odoo_addons/account_invoice_tax_required/tests/test_account_invoice_tax_required.py
odoo_addons/account_invoice_tax_required/static/description/icon.png
